gimmebio.text_plots-0.2.0-py3.6-nspkg.pth
gimmebio/text_plots/__init__.py
gimmebio/text_plots/cli.py
gimmebio/text_plots/histogram.py
gimmebio/text_plots/scatter_plot.py
gimmebio.text_plots-0.2.0.dist-info/METADATA
gimmebio.text_plots-0.2.0.dist-info/RECORD
gimmebio.text_plots-0.2.0.dist-info/WHEEL
gimmebio.text_plots-0.2.0.dist-info/namespace_packages.txt
gimmebio.text_plots-0.2.0.dist-info/top_level.txt
